typeguard/__init__.py
typeguard/_checkers.py
typeguard/_config.py
typeguard/_decorators.py
typeguard/_exceptions.py
typeguard/_functions.py
typeguard/_importhook.py
typeguard/_memo.py
typeguard/_pytest_plugin.py
typeguard/_suppression.py
typeguard/_transformer.py
typeguard/_union_transformer.py
typeguard/_utils.py
typeguard/py.typed
typeguard-4.4.1.dist-info/LICENSE
typeguard-4.4.1.dist-info/METADATA
typeguard-4.4.1.dist-info/WHEEL
typeguard-4.4.1.dist-info/entry_points.txt
typeguard-4.4.1.dist-info/top_level.txt
typeguard-4.4.1.dist-info/RECORD
