Metadata-Version: 2.1
Name: typeguard
Version: 4.4.1
Summary: Run-time type checker for Python
Author-email: Alex Grönholm <alex.gronholm@nextday.fi>
License: MIT
Project-URL: Documentation, https://typeguard.readthedocs.io/en/latest/
Project-URL: Change log, https://typeguard.readthedocs.io/en/latest/versionhistory.html
Project-URL: Source code, https://github.com/agronholm/typeguard
Project-URL: Issue tracker, https://github.com/agronholm/typeguard/issues
Classifier: Development Status :: 5 - Production/Stable
Classifier: Intended Audience :: Developers
Classifier: License :: OSI Approved :: MIT License
Classifier: Programming Language :: Python
Classifier: Programming Language :: Python :: 3
Classifier: Programming Language :: Python :: 3.9
Classifier: Programming Language :: Python :: 3.10
Classifier: Programming Language :: Python :: 3.11
Classifier: Programming Language :: Python :: 3.12
Classifier: Programming Language :: Python :: 3.13
Requires-Python: >=3.9
License-File: LICENSE
Requires-Dist: importlib_metadata>=3.6; python_version < "3.10"
Requires-Dist: typing_extensions>=4.10.0
Provides-Extra: test
Requires-Dist: coverage[toml]>=7; extra == "test"
Requires-Dist: pytest>=7; extra == "test"
Requires-Dist: mypy>=1.2.0; platform_python_implementation != "PyPy" and extra == "test"
Provides-Extra: doc
Requires-Dist: packaging; extra == "doc"
Requires-Dist: Sphinx>=7; extra == "doc"
Requires-Dist: sphinx-autodoc-typehints>=1.2.0; extra == "doc"
Requires-Dist: sphinx-rtd-theme>=1.3.0; extra == "doc"
